<?xml version='1.0' encoding='UTF-8'?>
<object id="3avMeuEfU9zr" classes="section" acceptedChildren=":Proteus-any" acceptedParents=":Proteus-document section">
  <properties>
    <stringProperty name=":Proteus-name" category="general"><![CDATA[Requisitos de conducta del sistema]]></stringProperty>
    <markdownProperty name="comments" category="general"><![CDATA[]]></markdownProperty>
  </properties>
  <children>
    <child id="6RNBTTVXnqKG"/>
    <child id="5shmdhABBv3M"/>
    <child id="5G33yVVq3zuy"/>
    <child id="679Nwb2hQbbb"/>
    <child id="4vxWrhVN8PXU"/>
    <child id="7teUijFJndND"/>
    <child id="8APDa7MrNe6i"/>
    <child id="347rLZcznAH2"/>
    <child id="576SLnkrQ7xf"/>
    <child id="CNuuqhGWCYVE"/>
    <child id="34J3LWNfCjqq"/>
    <child id="5UaxMEkZrUSY"/>
    <child id="6D5zmQuF9vbF"/>
  </children>
</object>
